part2/RegisterFile.v
// Testbench for reg_file module
module reg_file_tb;
    
    // Declare inputs to the reg_file
    reg [7:0] WRITEDATA;
    reg [2:0] WRITEREG, READREG1, READREG2;
    reg CLK, RESET, WRITEENABLE; 
    wire [7:0] REGOUT1, REGOUT2;
    
    reg_file myregfile(WRITEDATA, REGOUT1, REGOUT2, WRITEREG, READREG1, READREG2, WRITEENABLE, CLK, RESET);
       
    initial
    begin
        CLK = 1'b1;
        
        // generate files needed to plot the waveform using GTKWave
        $dumpfile("task2.vcd");
		$dumpvars(0, reg_file_tb);
        
        // assign values with time to input signals to see output 
        RESET = 1'b0;
        WRITEENABLE = 1'b0;
        
        #4
        RESET = 1'b1;
        READREG1 = 3'd0;
        READREG2 = 3'd4;
        
        #6
        RESET = 1'b0;
        
        #2
        WRITEREG = 3'd2;
        WRITEDATA = 8'd95;
        WRITEENABLE = 1'b1;
        
        #7
        WRITEENABLE = 1'b0;
        
        #1
        READREG1 = 3'd2;
        
        #7
        WRITEREG = 3'd1;
        WRITEDATA = 8'd28;
        WRITEENABLE = 1'b1;
        READREG1 = 3'd1;
        
        #8
        WRITEENABLE = 1'b0;
        
        #8
        WRITEREG = 3'd4;
        WRITEDATA = 8'd6;
        WRITEENABLE = 1'b1;
        
        #8
        WRITEDATA = 8'd15;
        WRITEENABLE = 1'b1;
        
        #10
        WRITEENABLE = 1'b0;
        
        #6
        WRITEREG = -3'd1;
        WRITEDATA = 8'd50;
        WRITEENABLE = 1'b1;
        
        #5
        WRITEENABLE = 1'b0;
        
        #10
        $finish;
    end
    
    // clock signal generation
    always
        #4 CLK = ~CLK;
        

endmodule



// Creat the module of reg_file
module reg_file(IN,OUT1,OUT2,INADDRESS,OUT1ADDRESS,OUT2ADDRESS,WRITE,CLK,RESET);
    input [2:0]OUT1ADDRESS,OUT2ADDRESS,INADDRESS;
    input signed[7:0] IN;
    input CLK,RESET,WRITE;
    output reg signed[7:0]OUT2,OUT1;
    
    // creat the 8-bit registers 8 because register file haas 8 register
    reg signed [7:0] register0,register1,register2,register3,register4,register5,register6,register7;

    // reset and write ooperation are synchronsied ther for reset and and write operation perform in postive clock edge
    always @(posedge CLK) begin
        // if reset is 0ne all register are set to zero
        if (RESET) begin
            #1
            register0 = 8'd0;
            register1 = 8'd0;
            register2 = 8'd0;
            register3 = 8'd0;
            register4 = 8'd0;
            register5 = 8'd0;
            register6 = 8'd0;
            register7 = 8'd0;
        end
        
        // if write is one then wirte the value in give address register
        if (WRITE) begin
            #1
            case (INADDRESS)
                3'b000 :register0 = IN; 
                3'b001 :register1 = IN; 
                3'b010 :register2 = IN; 
                3'b011 :register3 = IN; 
                3'b100 :register4 = IN; 
                3'b101 :register5 = IN; 
                3'b110 :register6 = IN;
                3'b111 :register7 = IN;
            endcase
        end

    end
    
    // 
    always @(OUT1ADDRESS,OUT2ADDRESS,CLK) begin
        #2
        case (OUT1ADDRESS)
            3'b000 : OUT1 = register0; 
            3'b001 : OUT1 = register1; 
            3'b010 : OUT1 = register2; 
            3'b011 : OUT1 = register3;
            3'b100 : OUT1 = register4; 
            3'b101 : OUT1 = register5; 
            3'b110 : OUT1 = register6;
            3'b111 : OUT1 = register7; 
        endcase

        case (OUT2ADDRESS)
            3'b000 : OUT2 = register0; 
            3'b001 : OUT2 = register1; 
            3'b010 : OUT2 = register2; 
            3'b011 : OUT2 = register3;
            3'b100 : OUT2 = register4; 
            3'b101 : OUT2 = register5; 
            3'b110 : OUT2 = register6;
            3'b111 : OUT2 = register7; 
        endcase
        
    end
endmodule

part2/reg_file_wavedata.vcd
$date
	Wed May 21 08:34:24 2025
$end
$version
	Icarus Verilog
$end
$timescale
	1s
$end
$scope module reg_file_tb $end
$var wire 8 ! REGOUT2 [7:0] $end
$var wire 8 " REGOUT1 [7:0] $end
$var reg 1 # CLK $end
$var reg 3 $ READREG1 [2:0] $end
$var reg 3 % READREG2 [2:0] $end
$var reg 1 & RESET $end
$var reg 8 ' WRITEDATA [7:0] $end
$var reg 1 ( WRITEENABLE $end
$var reg 3 ) WRITEREG [2:0] $end
$scope module myregfile $end
$var wire 1 # CLK $end
$var wire 8 * IN [7:0] $end
$var wire 3 + INADDRESS [2:0] $end
$var wire 3 , OUT1ADDRESS [2:0] $end
$var wire 3 - OUT2ADDRESS [2:0] $end
$var wire 1 & RESET $end
$var wire 1 ( WRITE $end
$var reg 8 . OUT1 [7:0] $end
$var reg 8 / OUT2 [7:0] $end
$var reg 8 0 register0 [7:0] $end
$var reg 8 1 register1 [7:0] $end
$var reg 8 2 register2 [7:0] $end
$var reg 8 3 register3 [7:0] $end
$var reg 8 4 register4 [7:0] $end
$var reg 8 5 register5 [7:0] $end
$var reg 8 6 register6 [7:0] $end
$var reg 8 7 register7 [7:0] $end
$upscope $end
$upscope $end
$enddefinitions $end
$comment Show the parameter values. $end
$dumpall
$end
#0
$dumpvars
bx 7
bx 6
bx 5
bx 4
bx 3
bx 2
bx 1
bx 0
bx /
bx .
bx -
bx ,
bx +
bx *
bx )
0(
bx '
0&
bx %
bx $
1#
bx "
bx !
$end
#4
0#
b100 %
b100 -
b0 $
b0 ,
1&
#8
1#
#9
b0 7
b0 6
b0 5
b0 4
b0 3
b0 2
b0 1
b0 0
#10
b0 !
b0 /
b0 "
b0 .
0&
#12
1(
b1011111 '
b1011111 *
b10 )
b10 +
0#
#16
1#
#17
b1011111 2
#19
0(
#20
b10 $
b10 ,
0#
#22
b1011111 "
b1011111 .
#24
1#
#27
b1 $
b1 ,
1(
b11100 '
b11100 *
b1 )
b1 +
#28
0#
#29
b0 "
b0 .
#32
1#
#33
b11100 1
#34
b11100 "
b11100 .
#35
0(
#36
0#
#40
1#
#43
1(
b110 '
b110 *
b100 )
b100 +
#44
0#
#48
1#
#49
b110 4
#50
b110 !
b110 /
#51
b1111 '
b1111 *
#52
0#
#56
1#
#57
b1111 4
#58
b1111 !
b1111 /
#60
0#
#61
0(
#64
1#
#67
1(
b110010 '
b110010 *
b111 )
b111 +
#68
0#
#72
1#
0(
