Part1/ALU.v
module testbench;
    reg signed[7:0]OPERAND1,OPERAND2;
    reg[2:0]ALUOP;
    wire signed[7:0] ALURESULT;
    // add the comment
    alu uut(OPERAND1,OPERAND2,ALURESULT,ALUOP);

    initial begin
        $monitor("TIME=%0t : OP1:%0d OP2:%0d ALUOP:%0b RESULT:%0d(%8b)", $time, OPERAND1, OPERAND2, ALUOP, ALURESULT,ALURESULT);
        $dumpfile("part1.vcd");
        $dumpvars(0,testbench);

        //Test forward




        
        OPERAND1=8'd0;
        OPERAND2=8'd65;
        ALUOP  =3'b000;
        #10;

        //Test add
        OPERAND1=8'd45;
        OPERAND2=8'd30;
        ALUOP  =3'b001;
        #10;

        //Test AND
        OPERAND1=8'b00100110;
        OPERAND2=8'b00111010;
        ALUOP  =3'b010;
        #10;

        //Test OR
        ALUOP  =3'b011;
        #10;

        $finish;
        
    end
    
endmodule




// the operation of forward
module FORWARD(DATA2,RESULT);
    input signed [7:0]DATA2;
    output reg signed [7:0] RESULT;
    
    always @(DATA2) begin
        //#1 RESULT=DATA2;
        RESULT=DATA2;
    end

endmodule



module ADD(DATA1,DATA2,RESULT);
    input signed [7:0]DATA1;
    input signed [7:0]DATA2;
    output reg signed  [7:0]RESULT;
    
    always @(DATA1,DATA2) begin
        // #2 RESULT=DATA1+DATA2;
        RESULT=DATA1+DATA2;
    end

endmodule



module AND(DATA1,DATA2,RESULT);
    input signed [7:0]DATA1;
    input signed[7:0]DATA2;
    output reg signed[7:0]RESULT;

    always @(DATA1,DATA2) begin
        // #1 RESULT=DATA1&DATA2;
        RESULT=DATA1&DATA2;
    end

endmodule



module OR(DATA1,DATA2,RESULT);
    input signed[7:0]DATA1;
    input signed[7:0]DATA2;
    output reg signed[7:0]RESULT;

    always @(DATA1,DATA2) begin
        // #1 RESULT=DATA1|DATA2;
        RESULT=DATA1|DATA2;
    end
    

endmodule

// module RESERVED();

// endmodule



module mux(I0,I1,I2,I3,SELECT,RESULT);
    input signed [7:0]I0,I1,I2,I3;
    input [2:0] SELECT;
    output reg signed[7:0] RESULT;

    always@(I0,I1,I2,I3,SELECT) begin
        case (SELECT)
            3'b000: #1 RESULT=I0;
            3'b001: #2 RESULT=I1;
            3'b010: #1 RESULT=I2;
            3'b011: #1 RESULT=I3; 
            default: RESULT=0;
        endcase
    end 


endmodule

module alu(DATA1,DATA2,RESULT,SELECT);
    input signed[7:0]DATA1;
    input signed[7:0]DATA2;
    input [2:0]SELECT;
    output signed[7:0]RESULT;

    
    wire signed [7:0]I0,I1,I2,I3;


    FORWARD uut(DATA2,I0);
    ADD add_unit(DATA1,DATA2,I1);
    AND and_unit(DATA1,DATA2,I2);
    OR or_unit(DATA1,DATA2,I3);
    // RESERVED res_unit();

    mux mux_unit(I0,I1,I2,I3,SELECT,RESULT);

endmodule

Part1/part1.vcd
$date
	Wed May 21 09:18:29 2025
$end
$version
	Icarus Verilog
$end
$timescale
	1s
$end
$scope module testbench $end
$var wire 8 ! ALURESULT [7:0] $end
$var reg 3 " ALUOP [2:0] $end
$var reg 8 # OPERAND1 [7:0] $end
$var reg 8 $ OPERAND2 [7:0] $end
$scope module uut $end
$var wire 8 % DATA1 [7:0] $end
$var wire 8 & DATA2 [7:0] $end
$var wire 3 ' SELECT [2:0] $end
$var wire 8 ( RESULT [7:0] $end
$var wire 8 ) I3 [7:0] $end
$var wire 8 * I2 [7:0] $end
$var wire 8 + I1 [7:0] $end
$var wire 8 , I0 [7:0] $end
$scope module add_unit $end
$var wire 8 - DATA1 [7:0] $end
$var wire 8 . DATA2 [7:0] $end
$var reg 8 / RESULT [7:0] $end
$upscope $end
$scope module and_unit $end
$var wire 8 0 DATA1 [7:0] $end
$var wire 8 1 DATA2 [7:0] $end
$var reg 8 2 RESULT [7:0] $end
$upscope $end
$scope module mux_unit $end
$var wire 8 3 I1 [7:0] $end
$var wire 8 4 I2 [7:0] $end
$var wire 3 5 SELECT [2:0] $end
$var wire 8 6 I3 [7:0] $end
$var wire 8 7 I0 [7:0] $end
$var reg 8 8 RESULT [7:0] $end
$upscope $end
$scope module or_unit $end
$var wire 8 9 DATA1 [7:0] $end
$var wire 8 : DATA2 [7:0] $end
$var reg 8 ; RESULT [7:0] $end
$upscope $end
$scope module uut $end
$var wire 8 < DATA2 [7:0] $end
$var reg 8 = RESULT [7:0] $end
$upscope $end
$upscope $end
$upscope $end
$enddefinitions $end
$comment Show the parameter values. $end
$dumpall
$end
#0
$dumpvars
bx =
b1000001 <
bx ;
b1000001 :
b0 9
bx 8
bx 7
bx 6
b0 5
bx 4
bx 3
bx 2
b1000001 1
b0 0
bx /
b1000001 .
b0 -
bx ,
bx +
bx *
bx )
bx (
b0 '
b1000001 &
b0 %
b1000001 $
b0 #
b0 "
bx !
$end
#1
b1000001 !
b1000001 (
b1000001 8
b1000001 ,
b1000001 7
b1000001 =
b1000001 )
b1000001 6
b1000001 ;
b0 *
b0 2
b0 4
#2
b1000001 +
b1000001 /
b1000001 3
#10
b1 "
b1 '
b1 5
b11110 $
b11110 &
b11110 .
b11110 1
b11110 :
b11110 <
b101101 #
b101101 %
b101101 -
b101101 0
b101101 9
#11
b11110 ,
b11110 7
b11110 =
b1100 *
b1100 2
b1100 4
b111111 )
b111111 6
b111111 ;
#12
b1001011 !
b1001011 (
b1001011 8
b1001011 +
b1001011 /
b1001011 3
#20
b1100 !
b1100 (
b1100 8
b10 "
b10 '
b10 5
b111010 $
b111010 &
b111010 .
b111010 1
b111010 :
b111010 <
b100110 #
b100110 %
b100110 -
b100110 0
b100110 9
#21
b100010 !
b100010 (
b100010 8
b111010 ,
b111010 7
b111010 =
b111110 )
b111110 6
b111110 ;
b100010 *
b100010 2
b100010 4
#22
b1100000 +
b1100000 /
b1100000 3
#30
b111110 !
b111110 (
b111110 8
b11 "
b11 '
b11 5
