part4/ALU.v
// ======================================================================
//                              ALU Module 
// Description: Complete ALU with multiple arithmetic and logic operations
// =======================================================================



// ------------------------------------------------
//           FORWARD Operation Module
// ------------------------------------------------
// Passes DATA2 to RESULT with 1 time unit delay

module FORWARD(DATA2,RESULT);
    input signed [7:0]DATA2;
    output reg signed [7:0] RESULT;
    
    // Combinational logic with propagation delay
    always @(DATA2) begin
        #1 RESULT=DATA2;         // 1 time unit delay
    end
endmodule



// --------------------------------------------
//          ADD Operation Module
// ---------------------------------------------
// Computes DATA1 + DATA2 with 2 time units delay

module ADD(DATA1,DATA2,RESULT);
    input signed [7:0]DATA1;
    input signed [7:0]DATA2;
    output reg signed  [7:0]RESULT;
   
    // Adder implementation 
    always @(DATA1,DATA2) begin
        #2 RESULT=DATA1+DATA2;    // 2 time unit delay
    end

endmodule



// -------------------------------------------
//          AND Operation Module
// --------------------------------------------
// Bitwise AND operation with 1 time unit delay

module AND(DATA1,DATA2,RESULT);
    input signed [7:0]DATA1;
    input signed[7:0]DATA2;
    output reg signed[7:0]RESULT;
    
    // Bitwise AND implementation 
    always @(DATA1,DATA2) begin
        #1 RESULT=DATA1&DATA2;    // 1 time unit delay
    end

endmodule


// -------------------------------------------
//         OR Operation Module
// -------------------------------------------
// Bitwise OR operation with 1 time unit delay

module OR(DATA1,DATA2,RESULT);
    input signed[7:0]DATA1;
    input signed[7:0]DATA2;
    output reg signed[7:0]RESULT;
    
    // Bitwise OR implementation
    always @(DATA1,DATA2) begin
        #1 RESULT=DATA1|DATA2;  // 1 time unit delay
    end
    

endmodule


// --------------------------------------
//         4:1 Multiplexer Module
// --------------------------------------
// Operation selector with zero-default safety

module mux(I0,I1,I2,I3,SELECT,RESULT);
    input signed [7:0]I0,I1,I2,I3;
    input [2:0] SELECT;
    output reg signed[7:0] RESULT;

    // Update RESULT based on SELECT value
    always@(I0,I1,I2,I3,SELECT) begin
        case (SELECT) 
            3'b000:  RESULT=I0;    // FORWARD output  
            3'b001:  RESULT=I1;    // ADD ouput
            3'b010:  RESULT=I2;    // AND ouput
            3'b011:  RESULT=I3;   // OR output 
            default: RESULT=0;
        endcase
    end 


endmodule

// ===========================================
//             Main ALU Module
// ===========================================
// Operations:
//               000: Forward DATA2
//               001: Addition
//               010: Bitwise AND
//               011: Bitwise OR
//               others: Output 0

module alu(DATA1,DATA2,RESULT,SELECT,ZERO);
    input signed[7:0]DATA1;
    input signed[7:0]DATA2;
    input [2:0]SELECT;
    output signed[7:0]RESULT;
    output ZERO;

    // Internal wires for operation outputs
    wire signed [7:0]I0,I1,I2,I3;

    // Instantiate each operation module
    FORWARD uut(DATA2,I0);
    ADD add_unit(DATA1,DATA2,I1);
    AND and_unit(DATA1,DATA2,I2);
    OR or_unit(DATA1,DATA2,I3);
    // RESERVED res_unit();
    
    // Instantiate multiplexer to select one of the operation outputs
    mux mux_unit(I0,I1,I2,I3,SELECT,RESULT);
    //chech data1-dat2 is eqault to zero
    assign ZERO=(RESULT==0)?1'b1:1'b0;

endmodule

part3/MUX_2.v
//============================================================================
//                      2-to-1 Multiplexer Module
// Selects between two 8-bit signed inputs based on select signal
//============================================================================

module mux_unit(DATA1,DATA2,select,OUTPUT);
    input signed[7:0]DATA1;    // First data input (selected when select = 0)
    input signed[7:0]DATA2;    // Second data input (selected when select = 1)
    input select;              // Selection control signal
    output signed[7:0]OUTPUT;  // Multiplexer output
    

    // Multiplexer logic using conditional operator
    // When select = 0: OUTPUT = DATA1
    // When select = 1: OUTPUT = DATA2
    assign OUTPUT= select ? DATA2 : DATA1;

endmodule



// module testbench;
//     reg signed[7:0] I0,I1;
//     reg select;
//     wire signed [7:0]OUTPUT; 

//     mux_unit mux(I0,I1,select,OUTPUT); 

//     initial begin
//        $monitor("I0: %0d I1: %0d  select:%0b OUTPUT:%0d",I0,I1,select,OUTPUT);

//        I0=8'd23;
//        I1=-8'd54;
//        select=1'b0;
//        #5;
//        select=1'b1;
//        #5;
//        $finish;

//     end


// endmodule

part4/twos_commplement.v
//============================================================================
//                        Two's Complement Converter Module
// Converts input number to its two's complement 
// Algorithm:   Two's complement = (~input) + 1 (invert bits and add 1)
//============================================================================

module twos_commplement(DATA_IN,DATA_OUT);
    input [7:0]DATA_IN;
    output reg signed[7:0] DATA_OUT;

    // Combinational logic block
    // Triggers whenever DATA_IN changes
    always @(DATA_IN) begin
        // Two's complement calculation with 1 delay
        // Step 1: Invert all bits (~DATA_IN)
        // Step 2: Add 1 to the inverted result
        // Result: Original number converted to its negative equivalent
        #1 DATA_OUT=(~DATA_IN)+1;
    end


endmodule 


// Testbench for Two's Complement Converter
// Tests conversion of positive numbers to their negative equivalents
// module testbench;
//     reg signed[7:0] in;
//     wire signed[7:0] out;

//     twos_commplement uut(in,out);

//     initial begin
//        $monitor("Time: %0t  Number : %d  Negative_number: %d",$time,in,out);
//        $dumpfile("two.vcd");
//        $dumpvars(0,testbench);

//        in=2;
//        #5
//        in=3;
//        #5;
//        in=8;
        
//     end


// endmodule

RegisterFile.v
module testbench;
reg [2:0] READREG1,READREG2,WRITEREG;
reg [7:0] WRITEDATA;
reg CLOCK,RESET,WRITEENABLE;
wire[7:0] REGOUT1,REGOUT2;

reg_file(WRITEDATA,REGOUT1,REGOUT2,WRITEREG,READREG1,READREG2,WRITEENABLE,CLOCK,RESET);

laways #5 CLOCK=~CLOCK;

initial begin
    // Initialize
    CLOCK = 0;
    RESET = 1;
    WRITEENABLE = 0;
    WRITEREG = 3'b000;
    WRITEDATA = 8'd0;
    READREG1 = 3'b000;
    READREG2 = 3'b001;

    #10 RESET = 0;

    // Write to register 2
    WRITEREG = 3'b010;
    WRITEDATA = 8'd77;
    WRITEENABLE = 1;
    #10;

    WRITEENABLE = 0;

    // Read from register 2
    READREG1 = 3'b010;
    READREG2 = 3'b010;
    #5;

    $display("REGOUT1: %d, REGOUT2: %d", REGOUT1, REGOUT2);

    #10 $finish;
end

    
endmodule 




module reg_file(IN,OUT1,OUT2,INADDRESS,OUT1ADDRESS,OUT2ADDRESS,WRITE,CLK,RESET);
    input [2:0]OUT1ADDRESS,OUT2ADDRESS,INADDRESS;
    input [7:0] IN;
    input CLK,RESET,WRITE;
    output reg [7:0]OUT2,OUT1;

    reg [7:0] register0,register1,register2,register3,register4,register5,register6,register7;


    always @(posedge CLK) begin
        if (WRITE==1'b1) begin
            #1;
            case (INADDRESS)
                3'b000 :register0 <= IN; 
                3'b001 :register1 <= IN; 
                3'b010 :register2 <= IN; 
                3'b011 :register3 <= IN; 
                3'b100 :register4 <= IN; 
                3'b101 :register5 <= IN; 
                3'b110 :register6 <= IN;
                3'b111 :register7 <= IN;
            endcase
        end

        if (RESET==1'b1) begin
            #1;
            register0 <= 0;
            register1 <= 0;
            register2 <= 0;
            register3 <= 0;
            register4 <= 0;
            register5 <= 0;
            register6 <= 0;
            register7 <= 0;
        end
    end

    always @(OUT1ADDRESS,OUT2ADDRESS,CLK) begin
        case (OUT1ADDRESS)
            #2;
            3'b000 : OUT1 = register0; 
            3'b001 : OUT1 = register1; 
            3'b010 : OUT1 = register2; 
            3'b011 : OUT1 = register3;
            3'b100 : OUT1 = register4; 
            3'b101 : OUT1 = register5; 
            3'b110 : OUT1 = register6;
            3'b111 : OUT1 = register7; 
        endcase

        case (OUT2ADDRESS)
            #2;
            3'b000 : OUT2 = register0; 
            3'b001 : OUT2 = register1; 
            3'b010 : OUT2 = register2; 
            3'b011 : OUT2 = register3;
            3'b100 : OUT2 = register4; 
            3'b101 : OUT2 = register5; 
            3'b110 : OUT2 = register6;
            3'b111 : OUT2 = register7; 
        endcase
        
    end
endmodule

part4/controlUnit.v
module control_unit(OPCODE,WRITEENABLE,ALUSRC,ALUOP,NEMUX,BRANCH,JUMP);
    input [7:0] OPCODE;          // 8-bit instruction opcode from instruction memory
    
    // Output control signals
    output reg [2:0] ALUOP;      // ALU operation selection (3-bit for 8 operations)
    output reg ALUSRC;           // ALU source selection (0=register, 1=immediate)
    output reg WRITEENABLE;      // Register write enable (1=write, 0=no write)
    output reg NEMUX;            // Negative/2's complement selection for subtraction
    output reg BRANCH;           // Branch control signal for conditional jumps
    output reg JUMP;             // Unconditional jump control signal


    // ============================================
    //           OPCODE DEFINITIONS
    // ============================================
                    // OP_ADD   = 8'b00000000;  
                    // OP_SUB   = 8'b00000001;  
                    // OP_AND   = 8'b00000010;  
                    // OP_OR    = 8'b00000011;  
                    // OP_MOV   = 8'b00000100;  
                    // OP_LOADI = 8'b00000101;
                    // OP_j     = 8'b00000110;    // Unconditional jump: PC = target_address
                    // OP_beq   = 8'b00000111;    // Branch if equal: if(RS1==RS2) PC = target_address
    

    //========================================================================
    //               CONTROL SIGNAL MEANINGS
    //=========================================================================
    // WRITEENABLE: 1 = Enable writing to register file, 0 = Disable
    // ALUSRC:      1 = Use register data, 0 = Use immediate data
    // NEMUX:       1 = Negate second operand (for subtraction), 0 = No negation
    // ALUOP:       3-bit code to select ALU operation


    always @(OPCODE) begin
        //Add 1 delay
        #1 
        
        if (OPCODE==8'b00000000) begin       // ADD 
            WRITEENABLE=1'b1;                // Enable register write
            ALUOP=3'b001;                    // ALU performs addition
            ALUSRC=1'b1;                     // Use register data 
            NEMUX=1'b0;                      // No negation needed 
            BRANCH=1'b0;                     // Not a branch instruction
            JUMP=1'b0;                       // Not a jump instruction
        end
        else if (OPCODE==8'b00000001) begin  // SUB 
            WRITEENABLE=1'b1;                // Enable register write
            ALUOP=3'b001;                    // ALU performs addition 
            ALUSRC=1'b1;                     // Use register data
            NEMUX=1'b1;                      // Enable negation for subtraction 
            BRANCH=1'b0;                     // Not a branch instruction
            JUMP=1'b0;                       // Not a jump instruction
        end
        else if (OPCODE==8'b00000010) begin  // AND 
            WRITEENABLE=1'b1;                // Enable register write
            ALUOP=3'b010;                    // ALU performs bitwise AND
            ALUSRC=1'b1;                     // Use register data 
            NEMUX=1'b0;                      // No negation needed 
            BRANCH=1'b0;                     // Not a branch instruction
            JUMP=1'b0;                       // Not a jump instruction
        end
        else if (OPCODE==8'b00000011) begin  // OR 
            WRITEENABLE=1'b1;                // Enable register write
            ALUOP=3'b011;                    // ALU performs bitwise OR
            ALUSRC=1'b1;                     // Use register data 
            NEMUX=1'b0;                      // No negation needed 
            BRANCH=1'b0;                     // Not a branch instruction
            JUMP=1'b0;                       // Not a jump instruction
        end
        else if (OPCODE==8'b00000100) begin  // Mov 
            WRITEENABLE=1'b1;                // Enable resiter write
            ALUOP=3'b000;                    // ALU performs forward operation 
            ALUSRC=1'b1;                     // Use register data 
            NEMUX=1'b0;                      // No negation needed
            BRANCH=1'b0;                     // Not a branch instruction
            JUMP=1'b0;                       // Not a jump instruction
        end
        else if (OPCODE==8'b00000101) begin  // LOADI
            WRITEENABLE=1'b1;                // Enable register write
            ALUOP=3'b000;                    // ALU performs forward operation
            ALUSRC=1'b0;                     // Use immediate data
            NEMUX=1'b0;                      // No negation needed 
            BRANCH=1'b0;                     // Not a branch instruction
            JUMP=1'b0;                       // Not a jump instruction
        end
        else if (OPCODE==8'b00000110) begin  // JUMP 
            WRITEENABLE=1'b0;                // No register write 
            ALUOP=3'b000;                    // ALU operation 
            ALUSRC=1'b0;                     // ALU source not used 
            NEMUX=1'b0;                      // Negation not used 
            BRANCH=1'b0;                     // Not a conditional branch
            JUMP=1'b1;                       // Enable unconditional jump
        end
        else if (OPCODE==8'b00000111) begin  // BEQ (Branch if Equal) o
            WRITEENABLE=1'b0;                // No register write 
            ALUOP=3'b001;                    // ALU performs subtraction for comparison
            ALUSRC=1'b1;                     // Use register data 
            NEMUX=1'b1;                      // Enable negation for subtraction comparison
            BRANCH=1'b1;                     // Enable conditional branching
            JUMP=1'b0;                       // Not an unconditional jump
        end
    end
endmodule

part4/instruction_memory.v
//============================================================================
//                               Instruction Decode Module
// Decodes 32-bit instruction word into constituent fields for CPU execution
// 
// Instruction Format (32-bit):
// [31:24] - OPCODE     (8 bits)  - Operation code
// [23:16] - OFFSET     (8 bits)  - Branch/Jump offset  
// [18:16] - WRITEREG   (3 bits)  - Destination register address
// [10:8]  - READREG1   (3 bits)  - First source register address  
// [7:0]   - IMMEDIATE  (8 bits)  - Immediate value/constant
// [2:0]   - READREG2   (3 bits)  - Second source register address
//============================================================================

module Instruction_decode(INSTRUCTION,OPCODE,IMMEDIATE,READREG1,READREG2,WRITEREG,OFFSET);
    input [31:0] INSTRUCTION;       // 32-bit instruction word from instruction memory
    output reg [7:0] OPCODE;        // 8-bit operation code
    output reg [2:0] READREG1;      // 3-bit address for first source register 
    output reg [2:0] READREG2;      // 3-bit address for second source register 
    output reg [2:0] WRITEREG;      // 3-bit address for destination register 
    output reg [7:0] IMMEDIATE;     // 8-bit immediate value for immediate operations
    output reg [7:0] OFFSET;        // 8-bit offset for branch/jump instructions

    // Decode logic triggers whenever instruction changes
    always @(INSTRUCTION) begin
        OPCODE = INSTRUCTION[31:24];
        READREG1 = INSTRUCTION[10:8];
        READREG2 = INSTRUCTION[2:0];
        WRITEREG = INSTRUCTION[18:16];
        IMMEDIATE = INSTRUCTION[7:0];
        OFFSET = INSTRUCTION[23:16];
    end

endmodule


// module testbench;
// reg [31:0] INSTRUCTION;
// wire [7:0] OPCODE,IMMEDIATE;
// wire [2:0] READREG1,READREG2,WRITEREG;

// Instruction_decode uut(INSTRUCTION,OPCODE,IMMEDIATE,READREG1,READREG2,WRITEREG);

// initial begin
//     $monitor("Time=%0t | INSTRUCTION=%b | OPCODE=%b | READREG1=%b | READREG2=%b | WRITEREG=%b | IMMEDIATE=%b",$time, INSTRUCTION, OPCODE, READREG1, READREG2, WRITEREG, IMMEDIATE);

//     // Test 1
//     INSTRUCTION = 32'b1001111_000011000_10101010_11110000;
    

//     $finish;
// end
// endmodule

part4/PC.v
// Program Counter (PC) Unit Module
// Handles PC increment, branching, and jumping
module pc_unit(RESET,CLK,PC,BRANCH,ZERO,JUMP,OFFSET);
    input RESET;           // Reset signal
    input CLK;             // Clock signal
    input BRANCH,ZERO,JUMP; // Control signals
    input signed [7:0]OFFSET; // Branch offset
    
    output reg [31:0] PC;           // Current program counter
    output signed [31:0]nextpc;     // Next PC value
    
    wire signed [31:0] PC_plus_four;    // PC + 4
    wire signed [31:0] BRANCH_TARGET;   // Branch target address
    
    wire Branching;                     // Branch condition met
    wire selector;                      // MUX selector
    wire signed [31:0]OFFSET_EXTENDED;  // Sign-extended offset
    
    // Branch condition: branch when ZERO flag is set AND BRANCH signal is active
    assign Branching=ZERO&BRANCH;
    
    // Select branch/jump target when jumping or branching
    assign selector=JUMP|Branching;
    
    // Calculate PC + 4 with 1 time unit delay
    assign #1 PC_plus_four=PC+4;
    
    // Sign extend 8-bit offset to 32-bit and shift left by 2 - word alignment
    assign OFFSET_EXTENDED= {{24{OFFSET[7]}}, OFFSET} << 2;
    
    // Calculate branch target address with 2 time unit delay
    assign #2 BRANCH_TARGET=OFFSET_EXTENDED+(PC+4);
    
    // MUX to select between PC+4 and branch target
    MUX_unit mux(PC_plus_four,BRANCH_TARGET,selector,nextpc);
    
    // Sequential logic for PC update
    always @(posedge CLK) begin
        if(RESET == 1'b1) begin 
            PC<= #1 0;        // Reset PC to 0 with delay
        end
        else begin
            #1 PC= nextpc;    // Update PC with next value
        end
    end
endmodule

// 2-to-1 Multiplexer Unit
// Selects between two 32-bit inputs based on selector
module MUX_unit(DATA1,DATA2,SELECTOR,RESULT);
    input [31:0]DATA1,DATA2;  
    output [31:0]RESULT;      
    input SELECTOR;          
    
    // Select DATA2 when SELECTOR is high, otherwise DATA1
    assign RESULT=(SELECTOR)?DATA2:DATA1;
endmodule

// module pc_tb;
// reg CLK,RESET;
// wire [31:0]pc;

// pc_unit PCtest(RESET,CLK,pc);

// initial begin 
//     CLK=1'b1;
//     forever #4 CLK=~CLK;
// end

// initial begin
//     #15
//     RESET=1;
//     #4
//     RESET=0;
//     #50
//     $finish;
// end

// initial begin
//     $monitor("Time = %3d | reset =%d  | pc= %d\n ",$time,RESET,pc);
// end

// endmodule

part4/CPU.v
`include "twos_commplement.v"
`include "RegisterFile.v"
`include "PC.v"
`include "MUX_2.v"
`include "instruction_memory.v"
`include "controlUnit.v"
`include "ALU.v"

module cpu(PC,INSTRUCTION,CLK,RESET);

// ==== Inputs and Outputs ====
input [31:0] INSTRUCTION;
input CLK, RESET;
output [31:0] PC; 


// ==== Internal Wires ====
// Instruction decoding
wire [7:0] OPCODE, IMMEDIATE,OFFSET;
wire [2:0] READREG1, READREG2, WRITEREG;


// Control Unit
wire WRITEENABLE, ALUSRC, NEMUX,BRANCH,JUMP;
wire [2:0] ALUOP;


// Register File
wire signed [7:0] REGOUT1, REGOUT2, WRITEDATA;

//ALU
wire ZERO;

// Two's Complement
wire signed [7:0] NEGATIVENUMBER;

// Mux outputs
wire signed [7:0] mux1_out, mux2_out;





// ==== Module Connections ====


// start to pc counter -> decode the instruction -> Control unit -> Register File->2's complemet->Mux1 ->mux2->ALU

// 1. Program Counter-done
pc_unit PCUNIT(RESET,CLK,PC,BRANCH,ZERO,JUMP,OFFSET);

// 2. Instruction Decode - done
Instruction_decode DECODER(INSTRUCTION,OPCODE,IMMEDIATE,READREG1,READREG2,WRITEREG,OFFSET);

// 3. Control Unit - done
control_unit control(OPCODE,WRITEENABLE,ALUSRC,ALUOP,NEMUX,BRANCH,JUMP);

// 4. Register File 
reg_file  REGFILE(WRITEDATA,REGOUT1,REGOUT2,WRITEREG,READREG1,READREG2,WRITEENABLE,CLK,RESET);

// 5. Two's Complement
twos_commplement twos(REGOUT2,NEGATIVENUMBER);


// 6. First Mux: Select between REGOUT2 and NEGATIVENUMBER
mux_unit MUX1(REGOUT2,NEGATIVENUMBER,NEMUX,mux1_out);

// 7. Second Mux: Select between mux1_out and IMMEDIATE
mux_unit MUX2(IMMEDIATE,mux1_out,ALUSRC,mux2_out);

// 8. ALU
alu ALU(REGOUT1,mux2_out,WRITEDATA,ALUOP,ZERO);


endmodule

part5/CPU_tb.v
// Computer Architecture (CO224) - Lab 05
// Design: Testbench of Integrated CPU of Simple Processor
// Author: Isuru Nawinne

`include "CPU.v"

module cpu_tb;

    reg CLK, RESET;
    wire [31:0] PC;
    reg [31:0] INSTRUCTION;
    
    /* 
    ------------------------
     SIMPLE INSTRUCTION MEM
    ------------------------
    */
    
    // TODO: Initialize an array of registers (8x1024) named 'instr_mem' to be used as instruction memory

    reg[7:0]instr_mem[1023:0];
    
    // TODO: Create combinational logic to support CPU instruction fetching, given the Program Counter(PC) value 
    //       (make sure you include the delay for instruction fetching here)
        
    always @(PC) begin
        #2
        INSTRUCTION={instr_mem[PC+3],instr_mem[PC+2],instr_mem[PC+1],instr_mem[PC]};
    end
        
        
    
    initial
    begin
        // Initialize instruction memory with the set of instructions you need execute on CPU
        
        // METHOD 1: manually loading instructions to instr_mem
        //{instr_mem[10'd3], instr_mem[10'd2], instr_mem[10'd1], instr_mem[10'd0]} = 32'b00000000000001000000000000000101;
        //{instr_mem[10'd7], instr_mem[10'd6], instr_mem[10'd5], instr_mem[10'd4]} = 32'b00000000000000100000000000001001;
        //{instr_mem[10'd11], instr_mem[10'd10], instr_mem[10'd9], instr_mem[10'd8]} = 32'b00000010000001100000010000000010;
        
        // METHOD 2: loading instr_mem content from instr_mem.mem file
        $readmemb("instr_mem.mem", instr_mem);
    end
    
    /* 
    -----
     CPU
    -----
    */
    cpu mycpu(PC, INSTRUCTION, CLK, RESET);

    initial
    begin
    
        // generate files needed to plot the waveform using GTKWave
        $dumpfile("cpu_wavedata.vcd");
		$dumpvars(3,cpu_tb,cpu_tb.mycpu.REGFILE.register0,cpu_tb.mycpu.REGFILE.register1,cpu_tb.mycpu.REGFILE.register2,cpu_tb.mycpu.REGFILE.register3,cpu_tb.mycpu.REGFILE.register4,cpu_tb.mycpu.REGFILE.register5,cpu_tb.mycpu.REGFILE.register6,cpu_tb.mycpu.REGFILE.register7);
        
        CLK = 1'b0;
        RESET = 1'b0;
        
        // TODO: Reset the CPU (by giving a pulse to RESET signal) to start the program execution
        #2
        RESET=1'b1;
        #4
        RESET=1'b0;
        // finish simulation after some time
        #500
        $finish;
        
    end
    
    // clock signal generation
    always
        #4 CLK = ~CLK;
        

endmodule

part4/cpu_wavedata.vcd
$date
	Wed Jun 18 15:22:25 2025
$end
$version
	Icarus Verilog
$end
$timescale
	1s
$end
$scope module cpu_tb $end
$var wire 32 ! PC [31:0] $end
$var reg 1 " CLK $end
$var reg 32 # INSTRUCTION [31:0] $end
$var reg 1 $ RESET $end
$scope module mycpu $end
$var wire 1 " CLK $end
$var wire 32 % INSTRUCTION [31:0] $end
$var wire 1 $ RESET $end
$var wire 8 & mux2_out [7:0] $end
$var wire 8 ' mux1_out [7:0] $end
$var wire 1 ( ZERO $end
$var wire 3 ) WRITEREG [2:0] $end
$var wire 1 * WRITEENABLE $end
$var wire 8 + WRITEDATA [7:0] $end
$var wire 8 , REGOUT2 [7:0] $end
$var wire 8 - REGOUT1 [7:0] $end
$var wire 3 . READREG2 [2:0] $end
$var wire 3 / READREG1 [2:0] $end
$var wire 32 0 PC [31:0] $end
$var wire 8 1 OPCODE [7:0] $end
$var wire 8 2 OFFSET [7:0] $end
$var wire 1 3 NEMUX $end
$var wire 8 4 NEGATIVENUMBER [7:0] $end
$var wire 1 5 JUMP $end
$var wire 8 6 IMMEDIATE [7:0] $end
$var wire 1 7 BRANCH $end
$var wire 1 8 ALUSRC $end
$var wire 3 9 ALUOP [2:0] $end
$scope module ALU $end
$var wire 1 ( ZERO $end
$var wire 3 : SELECT [2:0] $end
$var wire 8 ; RESULT [7:0] $end
$var wire 8 < I3 [7:0] $end
$var wire 8 = I2 [7:0] $end
$var wire 8 > I1 [7:0] $end
$var wire 8 ? I0 [7:0] $end
$var wire 8 @ DATA2 [7:0] $end
$var wire 8 A DATA1 [7:0] $end
$upscope $end
$scope module DECODER $end
$var wire 32 B INSTRUCTION [31:0] $end
$var reg 8 C IMMEDIATE [7:0] $end
$var reg 8 D OFFSET [7:0] $end
$var reg 8 E OPCODE [7:0] $end
$var reg 3 F READREG1 [2:0] $end
$var reg 3 G READREG2 [2:0] $end
$var reg 3 H WRITEREG [2:0] $end
$upscope $end
$scope module MUX1 $end
$var wire 1 3 select $end
$var wire 8 I OUTPUT [7:0] $end
$var wire 8 J DATA2 [7:0] $end
$var wire 8 K DATA1 [7:0] $end
$upscope $end
$scope module MUX2 $end
$var wire 8 L DATA1 [7:0] $end
$var wire 8 M DATA2 [7:0] $end
$var wire 1 8 select $end
$var wire 8 N OUTPUT [7:0] $end
$upscope $end
$scope module PCUNIT $end
$var wire 1 O Branching $end
$var wire 1 " CLK $end
$var wire 8 P OFFSET [7:0] $end
$var wire 1 $ RESET $end
$var wire 1 ( ZERO $end
$var wire 1 Q selector $end
$var wire 32 R nextpc [31:0] $end
$var wire 32 S PC_plus_four [31:0] $end
$var wire 32 T OFFSET_EXTENDED [31:0] $end
$var wire 1 5 JUMP $end
$var wire 32 U BRANCH_TARGET [31:0] $end
$var wire 1 7 BRANCH $end
$var reg 32 V PC [31:0] $end
$upscope $end
$scope module REGFILE $end
$var wire 1 " CLK $end
$var wire 8 W IN [7:0] $end
$var wire 3 X INADDRESS [2:0] $end
$var wire 3 Y OUT1ADDRESS [2:0] $end
$var wire 3 Z OUT2ADDRESS [2:0] $end
$var wire 1 $ RESET $end
$var wire 1 * WRITE $end
$var reg 8 [ OUT1 [7:0] $end
$var reg 8 \ OUT2 [7:0] $end
$var reg 8 ] register0 [7:0] $end
$var reg 8 ^ register1 [7:0] $end
$var reg 8 _ register2 [7:0] $end
$var reg 8 ` register3 [7:0] $end
$var reg 8 a register4 [7:0] $end
$var reg 8 b register5 [7:0] $end
$var reg 8 c register6 [7:0] $end
$var reg 8 d register7 [7:0] $end
$upscope $end
$scope module control $end
$var wire 8 e OPCODE [7:0] $end
$var reg 3 f ALUOP [2:0] $end
$var reg 1 8 ALUSRC $end
$var reg 1 7 BRANCH $end
$var reg 1 5 JUMP $end
$var reg 1 3 NEMUX $end
$var reg 1 * WRITEENABLE $end
$upscope $end
$scope module twos $end
$var wire 8 g DATA_IN [7:0] $end
$var reg 8 h DATA_OUT [7:0] $end
$upscope $end
$upscope $end
$upscope $end
$enddefinitions $end
$comment Show the parameter values. $end
$dumpall
$end
#0
$dumpvars
bx h
bx g
bx f
bx e
bx d
bx c
bx b
bx a
bx `
bx _
bx ^
bx ]
bx \
bx [
bx Z
bx Y
bx X
bx W
bx V
bx U
bx00 T
bx S
bx R
xQ
bx P
xO
bx N
bx M
bx L
bx K
bx J
bx I
bx H
bx G
bx F
bx E
bx D
bx C
bx B
bx A
bx @
bx ?
bx >
bx =
bx <
bx ;
bx :
bx 9
x8
x7
bx 6
x5
bx 4
x3
bx 2
bx 1
bx 0
bx /
bx .
bx -
bx ,
bx +
x*
bx )
x(
bx '
bx &
bx %
0$
bx #
0"
bx !
$end
#2
1$
#4
1"
#5
b0 !
b0 0
b0 V
b0 d
b0 c
b0 b
b0 a
b0 `
b0 _
b0 ^
b0 ]
#6
b100 S
0$
#7
b0 T
b0 2
b0 D
b0 P
b110 6
b110 C
b110 L
b0 )
b0 H
b0 X
b110 .
b110 G
b110 Z
b0 /
b0 F
b0 Y
b101 1
b101 E
b101 e
b101000000000000000000000110 #
b101000000000000000000000110 %
b101000000000000000000000110 B
#8
b100 R
0Q
0O
b110 &
b110 @
b110 N
05
07
03
08
b0 9
b0 :
b0 f
1*
0"
#9
0(
b110 +
b110 ;
b110 W
b0 '
b0 I
b0 M
b110 <
b0 =
b110 ?
b100 U
b0 ,
b0 K
b0 \
b0 g
b0 -
b0 A
b0 [
#10
b0 4
b0 J
b0 h
b110 >
#12
1"
#13
b100 !
b100 0
b100 V
b110 ]
#14
b1000 R
b1000 S
b110 -
b110 A
b110 [
#15
b100 T
b1 &
b1 @
b1 N
b1 2
b1 D
b1 P
b1 6
b1 C
b1 L
b1 )
b1 H
b1 X
b1 .
b1 G
b1 Z
b110 =
b101000000010000000000000001 #
b101000000010000000000000001 %
b101000000010000000000000001 B
b1000 U
#16
b1 +
b1 ;
b1 W
b111 <
b0 =
b1 ?
b111 >
0"
#17
b1100 U
#20
1"
#21
b1 ^
b1000 !
b1000 0
b1000 V
#22
b1100 R
b1 '
b1 I
b1 M
b1100 S
b1 ,
b1 K
b1 \
b1 g
#23
b1000 T
b11 &
b11 @
b11 N
b10 2
b10 D
b10 P
b11 6
b11 C
b11 L
b10 )
b10 H
b10 X
b11 .
b11 G
b11 Z
b11111111 4
b11111111 J
b11111111 h
b101000000100000000000000011 #
b101000000100000000000000011 %
b101000000100000000000000011 B
b10000 U
#24
b11 +
b11 ;
b11 W
b10 =
b11 ?
0"
#25
b0 '
b0 I
b0 M
b1001 >
b10100 U
b0 ,
b0 K
b0 \
b0 g
#26
b0 4
b0 J
b0 h
#28
1"
#29
b1100 !
b1100 0
b1100 V
b11 _
#30
b10000 R
b10000 S
#31
b1100 T
b1000 &
b1000 @
b1000 N
b11 2
b11 D
b11 P
b1000 6
b1000 C
b1000 L
b11 )
b11 H
b11 X
b0 .
b0 G
b0 Z
b101000000110000000000001000 #
b101000000110000000000001000 %
b101000000110000000000001000 B
b11000 U
#32
b1000 +
b1000 ;
b1000 W
b1110 <
b0 =
b1000 ?
0"
#33
b110 '
b110 I
b110 M
b1110 >
b11100 U
b110 ,
b110 K
b110 \
b110 g
#34
b11111010 4
b11111010 J
b11111010 h
#36
1"
#37
b1000 `
b10000 !
b10000 0
b10000 V
#38
b10100 R
b10100 S
#39
b0 T
b1 &
b1 @
b1 N
b0 2
b0 D
b0 P
b1 6
b1 C
b1 L
b0 )
b0 H
b0 X
b1 .
b1 G
b1 Z
b1 1
b1 E
b1 e
b1000000000000000000000001 #
b1000000000000000000000001 %
b1000000000000000000000001 B
b100000 U
#40
b11111010 '
b11111010 I
b11111010 M
b11111010 &
b11111010 @
b11111010 N
b1110 +
b1110 ;
b1110 W
b111 <
b1 ?
13
18
b1 9
b1 :
b1 f
0"
#41
1(
b0 +
b0 ;
b0 W
b11111110 <
b10 =
b11111010 ?
b0 >
b10100 U
b1 ,
b1 K
b1 \
b1 g
#42
b11111111 &
b11111111 @
b11111111 N
b11111111 '
b11111111 I
b11111111 M
b11111111 4
b11111111 J
b11111111 h
#43
b110 =
b11111111 <
b11111111 ?
#44
0(
b101 +
b101 ;
b101 W
b101 >
1"
#45
b10100 !
b10100 0
b10100 V
b101 ]
#46
b11000 R
b11000 S
b101 -
b101 A
b101 [
#47
b100 T
b1 2
b1 D
b1 P
b10 6
b10 C
b10 L
b1 )
b1 H
b1 X
b10 .
b10 G
b10 Z
b111 1
b111 E
b111 e
b101 =
b111000000010000000000000010 #
b111000000010000000000000010 %
b111000000010000000000000010 B
b11000 U
#48
b100 +
b100 ;
b100 W
17
0*
b100 >
0"
#49
b11100 U
b11 ,
b11 K
b11 \
b11 g
#50
b11111101 &
b11111101 @
b11111101 N
b11111101 '
b11111101 I
b11111101 M
b11111101 4
b11111101 J
b11111101 h
#51
b11111101 <
b11111101 ?
#52
b10 +
b10 ;
b10 W
b10 >
1"
#53
b11000 !
b11000 0
b11000 V
#54
b11100 R
b11100 S
#55
b11111111111111111111111111110100 T
b11111101 2
b11111101 D
b11111101 P
b0 6
b0 C
b0 L
b101 )
b101 H
b101 X
b0 .
b0 G
b0 Z
b110 1
b110 E
b110 e
b110111111010000000000000000 #
b110111111010000000000000000 %
b110111111010000000000000000 B
b100000 U
#56
b100000 R
1Q
b11 '
b11 I
b11 M
b0 &
b0 @
b0 N
b11111101 +
b11111101 ;
b11111101 W
15
07
03
08
b0 9
b0 :
b0 f
0"
